cla/__init__.py
cla/metrics.py
cla/unify.py
cla/gui/9555d1e5-ccaf-45ba-910e-ceb0d7d31234.csv
cla/gui/__init__.py
cla/gui/run.py
cla/gui/sample.csv
cla/gui/static/__init__.py
cla/gui/static/bootstrap.css
cla/gui/static/bootstrap.js
cla/gui/static/jquery-3.3.1.min.js
cla/gui/static/jquery.blockUI.js
cla/gui/static/jquery.form.min.js
cla/gui/static/sample.csv
cla/gui/templates/__init__.py
cla/gui/templates/home.html
cla/vis/__init__.py
cla/vis/confusion_matrix.py
cla/vis/feature_importance.py
cla/vis/plotComponents1D.py
cla/vis/plotComponents2D.py
cla/vis/plotComponents3D.py
cla/vis/plt2base64.py
cla/vis/unsupervised_dimension_reductions.py
cla-2.2.0.dist-info/LICENCE
cla-2.2.0.dist-info/METADATA
cla-2.2.0.dist-info/WHEEL
cla-2.2.0.dist-info/top_level.txt
cla-2.2.0.dist-info/RECORD
