Metadata-Version: 2.1
Name: cla
Version: 2.2.0
Summary: An integrated Python toolkit for classifiability analysis.
Home-page: http://pypi.python.org/pypi/cla/
Author: Zhang
Author-email: oo@zju.edu.cn
License: LICENSE.txt
License-File: LICENCE
Requires-Dist: flask
Requires-Dist: scikit-learn
Requires-Dist: scipy
Requires-Dist: uuid
Requires-Dist: pandas
Requires-Dist: matplotlib
Requires-Dist: numpy
Requires-Dist: seaborn
Requires-Dist: statsmodels
Requires-Dist: flaskwebgui
Requires-Dist: pyNNRW
